dbtlogs/__init__.py
dbtlogs/main.py
dbtlogs-0.3.dist-info/METADATA
dbtlogs-0.3.dist-info/WHEEL
dbtlogs-0.3.dist-info/entry_points.txt
dbtlogs-0.3.dist-info/top_level.txt
dbtlogs-0.3.dist-info/RECORD
